katzcom/__init__.py
katzcom/imaqt.py
katzcom-0.2.0.dist-info/WHEEL
katzcom-0.2.0.dist-info/METADATA
katzcom-0.2.0.dist-info/RECORD
