Metadata-Version: 2.1
Name: katzcom
Version: 0.2.0
Summary: Katz domain communications.
Author: Kevin Katz
Author-email: contact@kevinkatz.io
Requires-Python: >=3.7,<4.0
Classifier: Programming Language :: Python :: 3
Classifier: Programming Language :: Python :: 3.10
Classifier: Programming Language :: Python :: 3.7
Classifier: Programming Language :: Python :: 3.8
Classifier: Programming Language :: Python :: 3.9
Requires-Dist: paho-mqtt (>=1.6.1,<2.0.0)
Requires-Dist: python-osc (>=1.8.0,<2.0.0)
